Metadata-Version: 2.4
Name: mth308lib
Version: 1.0.0
Summary: A Python library implementing core numerical methods for MTH308: root-finding, linear systems, interpolation, and ODE solvers.
Author: Tanish Bansal, Shobhit Goel
Author-email: btanish23@iitk.ac.in, shobhitg23@iitk.ac.in
Classifier: Programming Language :: Python :: 3
Classifier: License :: OSI Approved :: MIT License
Classifier: Operating System :: OS Independent
Requires-Python: >=3.7
Requires-Dist: numpy
Requires-Dist: matplotlib
Dynamic: author
Dynamic: author-email
Dynamic: classifier
Dynamic: requires-dist
Dynamic: requires-python
Dynamic: summary
